__main__.py
typing_test_ydratec.py
typing_test_ydratec-0.2.5.dist-info/METADATA
typing_test_ydratec-0.2.5.dist-info/WHEEL
typing_test_ydratec-0.2.5.dist-info/entry_points.txt
typing_test_ydratec-0.2.5.dist-info/top_level.txt
typing_test_ydratec-0.2.5.dist-info/RECORD
