Metadata-Version: 2.1
Name: typing-test-ydratec
Version: 0.2.5
Summary: A simple typing test in a terminal.
Author-email: Clement Tardy <clementardy@icloud.com>
Requires-Dist: nltk >=3.8.1
Requires-Dist: reprint >=0.6.0
